{"cameraMode":{"drawMode":0,"name":"Shaded","section":"Shading Mode"},"sceneLighting":true,"audioPlay":false,"sceneViewState":{"showFog":true,"showMaterialUpdate":false,"showSkybox":true,"showFlares":true,"showImageEffects":true,"showParticleSystems":true},"in2DMode":false,"pivot":{"x":3.274470806121826,"y":13.122411727905274,"z":431.2623291015625},"rotation":{"x":-0.6959415674209595,"y":-0.009264742024242878,"z":0.00897992867976427,"w":-0.717984139919281},"size":30.63292121887207,"orthographic":false}